pyslide/__init__.py
pyslide/setup.py
pyslide/contour/__init__.py
pyslide/contour/_adjust.py
pyslide/contour/_check.py
pyslide/contour/_rela.py
pyslide/contour/_split.py
pyslide/contour/setup.py
pyslide/patch/__init__.py
pyslide/patch/_prop.py
pyslide/patch/_split.py
pyslide/patch/setup.py
pyslide/pyramid/__init__.py
pyslide/pyramid/_pyramid.py
pyslide/pyramid/setup.py
pyslide-0.5.0.dist-info/AUTHORS.md
pyslide-0.5.0.dist-info/LICENSE
pyslide-0.5.0.dist-info/METADATA
pyslide-0.5.0.dist-info/WHEEL
pyslide-0.5.0.dist-info/top_level.txt
pyslide-0.5.0.dist-info/RECORD
