Metadata-Version: 2.1
Name: pyslide
Version: 0.5.0
Summary: Python whole slide image analysis toolkit
Home-page: https://github.com/PingjunChen/pyslide
Author: Pingjun Chen
Author-email: pingjunchen@ieee.org
License: MIT
Platform: UNKNOWN
Classifier: Development Status :: 1 - Planning
Classifier: Intended Audience :: Developers
Classifier: Intended Audience :: Healthcare Industry
Classifier: Intended Audience :: Science/Research
Classifier: License :: OSI Approved :: MIT License
Classifier: Programming Language :: Python
Classifier: Programming Language :: Python :: 3
Classifier: Programming Language :: Python :: 3.8
Classifier: Topic :: Scientific/Engineering
License-File: LICENSE
License-File: AUTHORS.md
Requires-Dist: Pillow (>=8.1.1)
Requires-Dist: numpy (>=1.20.0)
Requires-Dist: openslide-python (>=1.1.2)
Requires-Dist: pycontour (>=1.4.0)
Requires-Dist: pydaily (>=0.4.3)
Requires-Dist: scikit-image (>=0.18.0)
Requires-Dist: setuptools (>=50.0.0)
Requires-Dist: shapely (>=1.6.4)
